Metadata-Version: 2.1
Name: nyaqqa
Version: 0.0.1
Summary: a library for weixin robot
Home-page: UNKNOWN
Author: pythonnic
Author-email: 2696047693@qq.com
License: MIT License
Keywords: get_friend_list Robot get_group_chat information
Platform: any
